sharp/__init__.py
sharp/downloader.py
sharp/main.py
sharp/request.py
sharp/response.py
sharp/spider.py
sharp/logger/__init__.py
sharp/request_manager/__init__.py
sharp/request_manager/request_filter/__init__.py
sharp/request_manager/utils/__init__.py
sharp/request_manager/utils/filter_class/__init__.py
sharp/request_manager/utils/filter_class/bloomfilter.py
sharp/request_manager/utils/filter_class/information_summary_filter/__init__.py
sharp/request_manager/utils/filter_class/information_summary_filter/memory_filter.py
sharp/request_manager/utils/filter_class/information_summary_filter/mysql_filter.py
sharp/request_manager/utils/filter_class/information_summary_filter/redis_filter.py
sharp/request_manager/utils/redis_tools/__init__.py
sharp/request_manager/utils/redis_tools/base.py
sharp/request_manager/utils/redis_tools/fifo_redis_queue.py
sharp/request_manager/utils/redis_tools/lifo_redis_queue.py
sharp/request_manager/utils/redis_tools/priority_redis_queue.py
sharp/request_manager/utils/redis_tools/redis_lock.py
sharp/request_wactcher/__init__.py
sharp_spider-1.5.8.dist-info/METADATA
sharp_spider-1.5.8.dist-info/WHEEL
sharp_spider-1.5.8.dist-info/top_level.txt
sharp_spider-1.5.8.dist-info/RECORD
